{
  "id": "lf_zq8a_tag_01_25_fragen_35_minuten_modernes_css",
  "name": "LF ZQ8a · Tag 01 · CSS Grundlagen und CSS statt LESS · 25 Fragen · 35 Minuten",
  "description": "25 thematisch passende Fragen zu Tag 01. Enthalten sind Code-Lesen-und-Verstehen, Zuordnungsfragen mit Post-its sowie Theoriefragen als Single Choice und Multiple Choice. Die Antworten sind gemischt und die drei Schwierigkeitsstufen sind enthalten.",
  "durationMinutes": 35,
  "timeLimitMinutes": 35,
  "questionCount": 25,
  "topics": {
    "101": "CSS-Einbindung, Syntax und Grundstruktur",
    "102": "Selektoren, Kaskade und Spezifität",
    "103": "Box-Modell, Einheiten und Farben",
    "104": "CSS Custom Properties und moderne CSS-Funktionen",
    "105": "CSS statt LESS: Struktur und Refactoring"
  },
  "topicLabels": {
    "101": "CSS-Einbindung, Syntax und Grundstruktur",
    "102": "Selektoren, Kaskade und Spezifität",
    "103": "Box-Modell, Einheiten und Farben",
    "104": "CSS Custom Properties und moderne CSS-Funktionen",
    "105": "CSS statt LESS: Struktur und Refactoring"
  },
  "difficultyLevels": {
    "leicht": "Grundlagen, Begriffe und direkte Wiedererkennung",
    "mittel": "Anwendung, Einordnung und typische Fehlerquellen",
    "schwer": "Transfer, Codeverständnis und fachliche Begründung"
  },
  "difficultyLabels": {
    "leicht": "Grundlagen, Begriffe und direkte Wiedererkennung",
    "mittel": "Anwendung, Einordnung und typische Fehlerquellen",
    "schwer": "Transfer, Codeverständnis und fachliche Begründung"
  },
  "questions": [
    {
      "type": "single-choice",
      "topic": "103",
      "difficulty": "schwer",
      "text": "Tag 1: Warum sollte die Lösung nicht nur optisch, sondern auch strukturell geprüft werden?",
      "options": [
        "Weil HTML dann keine Rolle spielt.",
        "Weil CSS sonst automatisch gelöscht wird.",
        "Weil Wartbarkeit, Kaskade, Responsivität und Bedienbarkeit fachlich relevant sind.",
        "Weil nur die Dateigröße zählt."
      ],
      "correct": [
        2
      ],
      "solution": "Weil Wartbarkeit, Kaskade, Responsivität und Bedienbarkeit fachlich relevant sind.",
      "explanation": "Technische Qualität ist mehr als ein erster optischer Eindruck.",
      "id": "T01-25-001"
    },
    {
      "type": "single-choice",
      "topic": "101",
      "difficulty": "leicht",
      "text": "Wie wird ein CSS-Kommentar geschrieben?",
      "options": [
        "<!-- Kommentar -->",
        "/* Kommentar */",
        "// Kommentar",
        "# Kommentar"
      ],
      "correct": [
        1
      ],
      "solution": "/* Kommentar */",
      "explanation": "CSS nutzt Blockkommentare mit /* ... */.",
      "id": "T01-25-002"
    },
    {
      "type": "matching-postits",
      "topic": "104",
      "difficulty": "mittel",
      "text": "Ordne moderne CSS-Techniken den früheren LESS-Ideen zu.<br><small>Ziehe die gelben Post-its auf die passenden Zielkarten.</small>",
      "items": [
        {
          "id": "l1",
          "text": "CSS Custom Properties"
        },
        {
          "id": "l3",
          "text": "calc()"
        },
        {
          "id": "l5",
          "text": ":root"
        },
        {
          "id": "l2",
          "text": "Komponentenklasse"
        },
        {
          "id": "l4",
          "text": "clamp()"
        }
      ],
      "targets": [
        {
          "id": "r4",
          "text": "flexibler Wert mit Minimum und Maximum",
          "match": "l4"
        },
        {
          "id": "r1",
          "text": "zentrale Werte wie Farben und Abstände",
          "match": "l1"
        },
        {
          "id": "r3",
          "text": "Berechnung direkt in CSS",
          "match": "l3"
        },
        {
          "id": "r2",
          "text": "wiederverwendbares Gestaltungsmuster",
          "match": "l2"
        },
        {
          "id": "r5",
          "text": "zentraler Bereich für globale Designwerte",
          "match": "l5"
        }
      ],
      "pairs": [
        {
          "leftId": "l1",
          "rightId": "r1"
        },
        {
          "leftId": "l5",
          "rightId": "r5"
        },
        {
          "leftId": "l3",
          "rightId": "r3"
        },
        {
          "leftId": "l4",
          "rightId": "r4"
        },
        {
          "leftId": "l2",
          "rightId": "r2"
        }
      ],
      "solution": "CSS Custom Properties → zentrale Werte wie Farben und Abstände<br>Komponentenklasse → wiederverwendbares Gestaltungsmuster<br>calc() → Berechnung direkt in CSS<br>clamp() → flexibler Wert mit Minimum und Maximum<br>:root → zentraler Bereich für globale Designwerte",
      "explanation": "Viele Präprozessor-Ideen sind heute in CSS direkt möglich.",
      "id": "T01-25-003"
    },
    {
      "type": "multiple-choice",
      "topic": "105",
      "difficulty": "mittel",
      "text": "Welche LESS-Funktionalitäten werden im neuen Lernfeld durch natives CSS oder Struktur ersetzt? <br><small>Mehrere Antworten möglich.</small>",
      "options": [
        "Operationen durch calc(), min(), max() oder clamp()",
        "Datenbankabfragen durch @font-face",
        "Variablen durch CSS Custom Properties",
        "Mixins durch Komponenten- und Utility-Klassen"
      ],
      "correct": [
        0,
        2,
        3
      ],
      "solution": "Variablen durch CSS Custom Properties<br>Operationen durch calc(), min(), max() oder clamp()<br>Mixins durch Komponenten- und Utility-Klassen",
      "explanation": "LESS-Schwerpunkte werden durch modernes CSS ersetzt.",
      "id": "T01-25-004"
    },
    {
      "type": "single-choice",
      "topic": "105",
      "difficulty": "leicht",
      "text": "Warum ist für dieses Lernfeld kein LESS-Compiler mehr notwendig?",
      "options": [
        "Weil alle Layouts als Bilder exportiert werden.",
        "Weil mit normalem CSS gearbeitet wird, das der Browser direkt versteht.",
        "Weil HTML keine Styles mehr benötigt.",
        "Weil CSS nur mit PHP funktioniert."
      ],
      "correct": [
        1
      ],
      "solution": "Weil mit normalem CSS gearbeitet wird, das der Browser direkt versteht.",
      "explanation": "Modernes CSS benötigt keinen Präprozessor.",
      "id": "T01-25-005"
    },
    {
      "type": "single-choice",
      "topic": "104",
      "difficulty": "mittel",
      "text": "Welche Hintergrundfarbe erhält <code>.box</code>?<br><div class=\"code-card\" style=\"max-width:900px;border-radius:16px;overflow:hidden;background:#102d42;box-shadow:0 10px 24px rgba(0,0,0,.16);font-family:Consolas,'Courier New',monospace;margin:12px 0;\"><div style=\"height:42px;background:#12334a;border-bottom:1px solid rgba(255,255,255,.14);display:flex;align-items:center;padding:0 16px;color:#fff;font-family:Arial,Helvetica,sans-serif;font-weight:700;\"><span style=\"width:11px;height:11px;background:#ff5f57;border-radius:50%;display:inline-block;margin-right:7px;\"></span><span style=\"width:11px;height:11px;background:#ffbd2e;border-radius:50%;display:inline-block;margin-right:7px;\"></span><span style=\"width:11px;height:11px;background:#28c840;border-radius:50%;display:inline-block;margin-right:13px;\"></span>style.css</div><pre style=\"margin:0;padding:18px 20px;color:#f8fbff;line-height:1.48;font-size:15px;white-space:pre-wrap;background:#102d42;\">:root { --main: #00abc7; }\n.box { background: var(--main); }</pre></div>",
      "options": [
        "weiß",
        "rot",
        "keine, weil var() nur in LESS gilt",
        "#00abc7"
      ],
      "correct": [
        3
      ],
      "solution": "#00abc7",
      "explanation": "Die Variable wird aus :root gelesen.",
      "id": "T01-25-006"
    },
    {
      "type": "single-choice",
      "topic": "104",
      "difficulty": "mittel",
      "text": "Welche Aussage zu <code>font-size: clamp(1.5rem, 4vw, 3rem)</code> ist korrekt?",
      "options": [
        "Die Regel ist nur in LESS gültig.",
        "Die Schriftgröße ist immer exakt 4vw.",
        "clamp() löscht den Text.",
        "Die Schriftgröße bleibt zwischen Minimum und Maximum und kann dazwischen flexibel wachsen."
      ],
      "correct": [
        3
      ],
      "solution": "Die Schriftgröße bleibt zwischen Minimum und Maximum und kann dazwischen flexibel wachsen.",
      "explanation": "clamp() kombiniert Mindestwert, flexiblen Wert und Maximalwert.",
      "id": "T01-25-007"
    },
    {
      "type": "multiple-choice",
      "topic": "101",
      "difficulty": "schwer",
      "text": "Welche Probleme können entstehen, wenn HTML-Struktur und CSS-Gestaltung ungeordnet vermischt werden? <br><small>Mehrere Antworten möglich.</small>",
      "options": [
        "Fehler in der Darstellung sind schwieriger einzugrenzen",
        "Änderungen werden schwerer nachvollziehbar",
        "Wiederverwendung von Komponenten wird erschwert",
        "Die Webseite wird automatisch semantisch korrekt"
      ],
      "correct": [
        0,
        1,
        2
      ],
      "solution": "Änderungen werden schwerer nachvollziehbar<br>Wiederverwendung von Komponenten wird erschwert<br>Fehler in der Darstellung sind schwieriger einzugrenzen",
      "explanation": "Trennung von Struktur und Gestaltung ist eine Grundlage wartbarer Webprojekte.",
      "id": "T01-25-008"
    },
    {
      "type": "single-choice",
      "topic": "103",
      "difficulty": "schwer",
      "text": "Ein Element hat <code>width: 300px</code>, <code>padding: 20px</code>, <code>border: 5px solid</code> und <code>box-sizing: content-box</code>. Wie breit ist es insgesamt?",
      "options": [
        "325px",
        "350px",
        "340px",
        "300px"
      ],
      "correct": [
        1
      ],
      "solution": "350px",
      "explanation": "300 + 2*20 + 2*5 = 350px.",
      "id": "T01-25-009"
    },
    {
      "type": "single-choice",
      "topic": "102",
      "difficulty": "mittel",
      "text": "Welche Farbe hat die Überschrift?<br><div class=\"code-card\" style=\"max-width:900px;border-radius:16px;overflow:hidden;background:#102d42;box-shadow:0 10px 24px rgba(0,0,0,.16);font-family:Consolas,'Courier New',monospace;margin:12px 0;\"><div style=\"height:42px;background:#12334a;border-bottom:1px solid rgba(255,255,255,.14);display:flex;align-items:center;padding:0 16px;color:#fff;font-family:Arial,Helvetica,sans-serif;font-weight:700;\"><span style=\"width:11px;height:11px;background:#ff5f57;border-radius:50%;display:inline-block;margin-right:7px;\"></span><span style=\"width:11px;height:11px;background:#ffbd2e;border-radius:50%;display:inline-block;margin-right:7px;\"></span><span style=\"width:11px;height:11px;background:#28c840;border-radius:50%;display:inline-block;margin-right:13px;\"></span>style.css</div><pre style=\"margin:0;padding:18px 20px;color:#f8fbff;line-height:1.48;font-size:15px;white-space:pre-wrap;background:#102d42;\">h1 { color: blue; }\nh1 { color: green; }</pre></div>",
      "options": [
        "grün",
        "blau",
        "rot",
        "keine Farbe"
      ],
      "correct": [
        0
      ],
      "solution": "grün",
      "explanation": "Bei gleicher Spezifität gewinnt die spätere Regel.",
      "id": "T01-25-010"
    },
    {
      "type": "single-choice",
      "topic": "105",
      "difficulty": "schwer",
      "text": "Welche Vorgehensweise ist beim Refactoring von LESS nach CSS fachlich sauber?",
      "options": [
        "LESS-Konstrukte identifizieren, passende CSS-Alternativen wählen, Ergebnis im Browser testen.",
        "Alle HTML-Dateien löschen und nur Fonts behalten.",
        "Alle Selektoren mit !important versehen.",
        "LESS-Dateien umbenennen, ohne Inhalt zu prüfen."
      ],
      "correct": [
        0
      ],
      "solution": "LESS-Konstrukte identifizieren, passende CSS-Alternativen wählen, Ergebnis im Browser testen.",
      "explanation": "Refactoring braucht Analyse, Umsetzung und Kontrolle.",
      "id": "T01-25-011"
    },
    {
      "type": "matching-postits",
      "topic": "105",
      "difficulty": "schwer",
      "text": "Ordne Refactoring-Schritte zu.<br><small>Ziehe die gelben Post-its auf die passenden Zielkarten.</small>",
      "items": [
        {
          "id": "l3",
          "text": "Selektoren bereinigen"
        },
        {
          "id": "l2",
          "text": "Variablen übertragen"
        },
        {
          "id": "l5",
          "text": "Dateien strukturieren"
        },
        {
          "id": "l1",
          "text": "LESS-Datei prüfen"
        },
        {
          "id": "l4",
          "text": "Browser testen"
        }
      ],
      "targets": [
        {
          "id": "r4",
          "text": "Darstellung und Responsivität kontrollieren",
          "match": "l4"
        },
        {
          "id": "r2",
          "text": "Werte in :root als Custom Properties ablegen",
          "match": "l2"
        },
        {
          "id": "r5",
          "text": "CSS, Bilder und Fonts sauber ablegen",
          "match": "l5"
        },
        {
          "id": "r1",
          "text": "Welche Konstrukte werden benutzt?",
          "match": "l1"
        },
        {
          "id": "r3",
          "text": "Verschachtelung in klare CSS-Regeln überführen",
          "match": "l3"
        }
      ],
      "pairs": [
        {
          "leftId": "l3",
          "rightId": "r3"
        },
        {
          "leftId": "l2",
          "rightId": "r2"
        },
        {
          "leftId": "l4",
          "rightId": "r4"
        },
        {
          "leftId": "l5",
          "rightId": "r5"
        },
        {
          "leftId": "l1",
          "rightId": "r1"
        }
      ],
      "solution": "LESS-Datei prüfen → Welche Konstrukte werden benutzt?<br>Variablen übertragen → Werte in :root als Custom Properties ablegen<br>Selektoren bereinigen → Verschachtelung in klare CSS-Regeln überführen<br>Browser testen → Darstellung und Responsivität kontrollieren<br>Dateien strukturieren → CSS, Bilder und Fonts sauber ablegen",
      "explanation": "Refactoring ist ein geordneter Umbau, kein reines Umbenennen.",
      "id": "T01-25-012"
    },
    {
      "type": "single-choice",
      "topic": "102",
      "difficulty": "leicht",
      "text": "Welcher Selektor spricht das Element mit der ID <code>main</code> an?",
      "options": [
        "#main",
        "@main",
        "main",
        ".main"
      ],
      "correct": [
        0
      ],
      "solution": "#main",
      "explanation": "ID-Selektoren beginnen mit #.",
      "id": "T01-25-013"
    },
    {
      "type": "single-choice",
      "topic": "101",
      "difficulty": "leicht",
      "text": "Welches HTML-Element bindet eine externe CSS-Datei korrekt ein?",
      "options": [
        "<script src=\"css/style.css\"></script>",
        "<style src=\"style.css\"></style>",
        "<css href=\"style.css\">",
        "<link rel=\"stylesheet\" href=\"css/style.css\">"
      ],
      "correct": [
        3
      ],
      "solution": "<link rel=\"stylesheet\" href=\"css/style.css\">",
      "explanation": "Externe Stylesheets werden im head über link eingebunden.",
      "id": "T01-25-014"
    },
    {
      "type": "multiple-choice",
      "topic": "104",
      "difficulty": "mittel",
      "text": "Tag 1: Welche Punkte sprechen für eine geordnete CSS-Datei? <br><small>Mehrere Antworten möglich.</small>",
      "options": [
        "Komponenten können leichter gepflegt werden",
        "Klassennamen sollten absichtlich unverständlich sein",
        "Regeln lassen sich schneller finden",
        "Doppelte Deklarationen fallen eher auf"
      ],
      "correct": [
        0,
        2,
        3
      ],
      "solution": "Regeln lassen sich schneller finden<br>Doppelte Deklarationen fallen eher auf<br>Komponenten können leichter gepflegt werden",
      "explanation": "Ordnung in CSS unterstützt Wartbarkeit und Fehlersuche.",
      "id": "T01-25-015"
    },
    {
      "type": "matching-postits",
      "topic": "102",
      "difficulty": "leicht",
      "text": "Ordne die Selektoren ihrer Bedeutung zu.<br><small>Ziehe die gelben Post-its auf die passenden Zielkarten.</small>",
      "items": [
        {
          "id": "l5",
          "text": "a:hover"
        },
        {
          "id": "l1",
          "text": ".card"
        },
        {
          "id": "l3",
          "text": "article"
        },
        {
          "id": "l4",
          "text": "*"
        },
        {
          "id": "l2",
          "text": "#main"
        }
      ],
      "targets": [
        {
          "id": "r5",
          "text": "Link beim Überfahren mit der Maus",
          "match": "l5"
        },
        {
          "id": "r1",
          "text": "Elemente mit der Klasse card",
          "match": "l1"
        },
        {
          "id": "r4",
          "text": "Alle Elemente",
          "match": "l4"
        },
        {
          "id": "r2",
          "text": "Element mit der ID main",
          "match": "l2"
        },
        {
          "id": "r3",
          "text": "Alle article-Elemente",
          "match": "l3"
        }
      ],
      "pairs": [
        {
          "leftId": "l5",
          "rightId": "r5"
        },
        {
          "leftId": "l1",
          "rightId": "r1"
        },
        {
          "leftId": "l2",
          "rightId": "r2"
        },
        {
          "leftId": "l4",
          "rightId": "r4"
        },
        {
          "leftId": "l3",
          "rightId": "r3"
        }
      ],
      "solution": ".card → Elemente mit der Klasse card<br>#main → Element mit der ID main<br>article → Alle article-Elemente<br>* → Alle Elemente<br>a:hover → Link beim Überfahren mit der Maus",
      "explanation": "Selektoren legen fest, welche Elemente gestaltet werden.",
      "id": "T01-25-016"
    },
    {
      "type": "single-choice",
      "topic": "103",
      "difficulty": "schwer",
      "text": "Ein Element hat <code>width: 300px</code>, <code>padding: 20px</code>, <code>border: 5px solid</code> und <code>box-sizing: border-box</code>. Welche Aussage ist korrekt?",
      "options": [
        "Die Gesamtbreite bleibt 300px.",
        "border-box funktioniert nur in LESS.",
        "Padding wird nicht dargestellt.",
        "Die Gesamtbreite wird 350px."
      ],
      "correct": [
        0
      ],
      "solution": "Die Gesamtbreite bleibt 300px.",
      "explanation": "Bei border-box sind Padding und Border Teil der angegebenen Breite.",
      "id": "T01-25-017"
    },
    {
      "type": "single-choice",
      "topic": "103",
      "difficulty": "schwer",
      "text": "Welche Aussage ist korrekt?<br><div class=\"code-card\" style=\"max-width:900px;border-radius:16px;overflow:hidden;background:#102d42;box-shadow:0 10px 24px rgba(0,0,0,.16);font-family:Consolas,'Courier New',monospace;margin:12px 0;\"><div style=\"height:42px;background:#12334a;border-bottom:1px solid rgba(255,255,255,.14);display:flex;align-items:center;padding:0 16px;color:#fff;font-family:Arial,Helvetica,sans-serif;font-weight:700;\"><span style=\"width:11px;height:11px;background:#ff5f57;border-radius:50%;display:inline-block;margin-right:7px;\"></span><span style=\"width:11px;height:11px;background:#ffbd2e;border-radius:50%;display:inline-block;margin-right:7px;\"></span><span style=\"width:11px;height:11px;background:#28c840;border-radius:50%;display:inline-block;margin-right:13px;\"></span>style.css</div><pre style=\"margin:0;padding:18px 20px;color:#f8fbff;line-height:1.48;font-size:15px;white-space:pre-wrap;background:#102d42;\">.hero {\n  padding: 2rem;\n  margin-bottom: 3rem;\n  border-radius: 1rem;\n}\n</pre></div>",
      "options": [
        "Der Code definiert eine Datenbanktabelle.",
        "Innenabstand, Außenabstand unten und abgerundete Ecken werden gesetzt.",
        "border-radius löscht den Rahmen.",
        "margin-bottom steuert den Innenabstand."
      ],
      "correct": [
        1
      ],
      "solution": "Innenabstand, Außenabstand unten und abgerundete Ecken werden gesetzt.",
      "explanation": "Die Eigenschaften betreffen das Box-Modell und die Darstellung.",
      "id": "T01-25-018"
    },
    {
      "type": "single-choice",
      "topic": "104",
      "difficulty": "mittel",
      "text": "Warum werden globale CSS-Variablen oft in <code>:root</code> definiert?",
      "options": [
        "Sie deaktivieren die Kaskade vollständig.",
        "Sie werden dadurch automatisch zu SQL-Variablen.",
        "Sie funktionieren nur bei Bildern.",
        "Sie sind dann zentral verfügbar und gut wartbar."
      ],
      "correct": [
        3
      ],
      "solution": "Sie sind dann zentral verfügbar und gut wartbar.",
      "explanation": ":root ist ein sinnvoller zentraler Ort für Design-Tokens.",
      "id": "T01-25-019"
    },
    {
      "type": "single-choice",
      "topic": "103",
      "difficulty": "leicht",
      "text": "Welche Eigenschaft steuert den Innenabstand eines Elements?",
      "options": [
        "border-radius",
        "display",
        "margin",
        "padding"
      ],
      "correct": [
        3
      ],
      "solution": "padding",
      "explanation": "Padding ist der Abstand zwischen Inhalt und Rahmen.",
      "id": "T01-25-020"
    },
    {
      "type": "single-choice",
      "topic": "102",
      "difficulty": "mittel",
      "text": "Welche Elemente werden angesprochen?<br><div class=\"code-card\" style=\"max-width:900px;border-radius:16px;overflow:hidden;background:#102d42;box-shadow:0 10px 24px rgba(0,0,0,.16);font-family:Consolas,'Courier New',monospace;margin:12px 0;\"><div style=\"height:42px;background:#12334a;border-bottom:1px solid rgba(255,255,255,.14);display:flex;align-items:center;padding:0 16px;color:#fff;font-family:Arial,Helvetica,sans-serif;font-weight:700;\"><span style=\"width:11px;height:11px;background:#ff5f57;border-radius:50%;display:inline-block;margin-right:7px;\"></span><span style=\"width:11px;height:11px;background:#ffbd2e;border-radius:50%;display:inline-block;margin-right:7px;\"></span><span style=\"width:11px;height:11px;background:#28c840;border-radius:50%;display:inline-block;margin-right:13px;\"></span>style.css</div><pre style=\"margin:0;padding:18px 20px;color:#f8fbff;line-height:1.48;font-size:15px;white-space:pre-wrap;background:#102d42;\">.nav a:hover { color: #00abc7; }</pre></div>",
      "options": [
        "Links innerhalb von .nav beim Überfahren mit der Maus",
        "Alle div-Elemente",
        "Alle Überschriften",
        "Nur Bilder mit der Klasse nav"
      ],
      "correct": [
        0
      ],
      "solution": "Links innerhalb von .nav beim Überfahren mit der Maus",
      "explanation": ":hover ist eine Pseudoklasse.",
      "id": "T01-25-021"
    },
    {
      "type": "single-choice",
      "topic": "105",
      "difficulty": "mittel",
      "text": "Welche Ordnerstruktur ist für ein kleines CSS-Projekt sinnvoll?",
      "options": [
        "Nur eine PDF-Datei",
        "index.html, assets/css oder css/style.css, ggf. images und fonts",
        "Alle Dateien ohne Namen direkt in C:\\Windows",
        "style.less als einzige erlaubte Datei"
      ],
      "correct": [
        1
      ],
      "solution": "index.html, assets/css oder css/style.css, ggf. images und fonts",
      "explanation": "Klare Projektstruktur erleichtert Einstieg und Abgabe.",
      "id": "T01-25-022"
    },
    {
      "type": "multiple-choice",
      "topic": "104",
      "difficulty": "mittel",
      "text": "Welche CSS-Funktionen eignen sich für moderne flexible Layouts? <br><small>Mehrere Antworten möglich.</small>",
      "options": [
        "DROP TABLE()",
        "min()",
        "calc()",
        "clamp()"
      ],
      "correct": [
        1,
        2,
        3
      ],
      "solution": "calc()<br>clamp()<br>min()",
      "explanation": "calc, clamp und min/max sind moderne native CSS-Funktionen.",
      "id": "T01-25-023"
    },
    {
      "type": "matching-postits",
      "topic": "103",
      "difficulty": "leicht",
      "text": "Ordne die Box-Modell-Begriffe zu.<br><small>Ziehe die gelben Post-its auf die passenden Zielkarten.</small>",
      "items": [
        {
          "id": "l1",
          "text": "content"
        },
        {
          "id": "l4",
          "text": "margin"
        },
        {
          "id": "l5",
          "text": "box-sizing"
        },
        {
          "id": "l2",
          "text": "padding"
        },
        {
          "id": "l3",
          "text": "border"
        }
      ],
      "targets": [
        {
          "id": "r4",
          "text": "Außenabstand",
          "match": "l4"
        },
        {
          "id": "r2",
          "text": "Innenabstand",
          "match": "l2"
        },
        {
          "id": "r3",
          "text": "Rahmen",
          "match": "l3"
        },
        {
          "id": "r1",
          "text": "eigentliche Inhaltsfläche",
          "match": "l1"
        },
        {
          "id": "r5",
          "text": "Art der Breitenberechnung",
          "match": "l5"
        }
      ],
      "pairs": [
        {
          "leftId": "l2",
          "rightId": "r2"
        },
        {
          "leftId": "l4",
          "rightId": "r4"
        },
        {
          "leftId": "l1",
          "rightId": "r1"
        },
        {
          "leftId": "l3",
          "rightId": "r3"
        },
        {
          "leftId": "l5",
          "rightId": "r5"
        }
      ],
      "solution": "content → eigentliche Inhaltsfläche<br>padding → Innenabstand<br>border → Rahmen<br>margin → Außenabstand<br>box-sizing → Art der Breitenberechnung",
      "explanation": "Das Box-Modell ist Grundlage jeder Layoutberechnung.",
      "id": "T01-25-024"
    },
    {
      "type": "single-choice",
      "topic": "103",
      "difficulty": "leicht",
      "text": "Welche Einheit orientiert sich an der Schriftgröße des Wurzelelements?",
      "options": [
        "vh",
        "%",
        "rem",
        "px"
      ],
      "correct": [
        2
      ],
      "solution": "rem",
      "explanation": "rem bezieht sich auf die Root-Schriftgröße.",
      "id": "T01-25-025"
    }
  ]
}